adrishyam/__init__.py
adrishyam/dehaze.py
adrishyam-0.1.1.dist-info/licenses/LICENSE
adrishyam-0.1.1.dist-info/METADATA
adrishyam-0.1.1.dist-info/WHEEL
adrishyam-0.1.1.dist-info/top_level.txt
adrishyam-0.1.1.dist-info/RECORD
