Metadata-Version: 2.4
Name: adrishyam
Version: 0.1.1
Summary: A Python package for image dehazing using Dark Channel Prior
Home-page: https://github.com/Krushna-007/adrishyam
Author: Krushna Parmar, Saumya Gohil
Author-email: parmarkrushna7@gmail.com, gohilsaumya16@gmail.com
Keywords: image-processing dehazing dark-channel-prior computer-vision
Classifier: Programming Language :: Python :: 3
Classifier: License :: OSI Approved :: MIT License
Classifier: Operating System :: OS Independent
Classifier: Topic :: Scientific/Engineering :: Image Processing
Classifier: Development Status :: 4 - Beta
Requires-Python: >=3.8
License-File: LICENSE
Requires-Dist: numpy>=1.24.0
Requires-Dist: pillow>=10.0.0
Requires-Dist: matplotlib>=3.7.0
Requires-Dist: scipy>=1.10.0
Dynamic: author
Dynamic: author-email
Dynamic: classifier
Dynamic: description
Dynamic: description-content-type
Dynamic: home-page
Dynamic: keywords
Dynamic: license-file
Dynamic: requires-dist
Dynamic: requires-python
Dynamic: summary
